drf_ignore_slash_middleware/__init__.py
drf_ignore_slash_middleware/slash_ignore_middleware.py
drf_ignore_slash_middleware-0.0.1.dist-info/DESCRIPTION.rst
drf_ignore_slash_middleware-0.0.1.dist-info/METADATA
drf_ignore_slash_middleware-0.0.1.dist-info/RECORD
drf_ignore_slash_middleware-0.0.1.dist-info/WHEEL
drf_ignore_slash_middleware-0.0.1.dist-info/metadata.json
drf_ignore_slash_middleware-0.0.1.dist-info/top_level.txt
