Metadata-Version: 2.0
Name: drf-ignore-slash-middleware
Version: 0.0.1
Summary: Django middleware that makes urls ending with and without slashes equivelent 
Home-page: https://github.com/ah450/drf-ignore-slash-middleware
Author: Ahmed Hisham Ismail
Author-email: ahm3d.hisham@gmail.com
License: MIT
Platform: UNKNOWN
Classifier: Environment :: Web Environment
Classifier: Framework :: Django
Classifier: Framework :: Django :: 1.10
Classifier: Intended Audience :: Developers
Classifier: Programming Language :: Python
Classifier: Programming Language :: Python :: 3
Classifier: Topic :: Internet :: WWW/HTTP
Classifier: License :: OSI Approved :: MIT License
